acryo/__init__.py
acryo/_dask.py
acryo/_reader.py
acryo/_rotation.py
acryo/_typed_scipy.py
acryo/_types.py
acryo/_utils.py
acryo/ctf.py
acryo/simulator.py
acryo/alignment/__init__.py
acryo/alignment/_base.py
acryo/alignment/_bound.py
acryo/alignment/_concrete.py
acryo/backend/__init__.py
acryo/backend/_api.py
acryo/backend/_bandpass.py
acryo/backend/_fsc.py
acryo/backend/_mesh.py
acryo/backend/_missing_wedge.py
acryo/backend/_pcc.py
acryo/backend/_upsample.py
acryo/backend/_zncc.py
acryo/deconv/__init__.py
acryo/deconv/_wiener.py
acryo/loader/__init__.py
acryo/loader/_base.py
acryo/loader/_batch.py
acryo/loader/_extracted.py
acryo/loader/_group.py
acryo/loader/_loader.py
acryo/loader/_misc.py
acryo/loader/_mock.py
acryo/molecules/__init__.py
acryo/molecules/_cut.py
acryo/molecules/_group.py
acryo/molecules/_rotation.py
acryo/molecules/core.py
acryo/pick/__init__.py
acryo/pick/_base.py
acryo/pick/_concrete.py
acryo/pipe/__init__.py
acryo/pipe/_classes.py
acryo/pipe/_curry.py
acryo/pipe/_imread.py
acryo/pipe/_masking.py
acryo/pipe/_transform.py
acryo/testing/__init__.py
acryo/testing/_templates.py
acryo/testing/core.py
acryo/tilt/__init__.py
acryo/tilt/_base.py
acryo/tilt/_single.py
acryo/tilt/_utils.py
acryo/tilt/core.py
acryo-0.6.0.dist-info/METADATA
acryo-0.6.0.dist-info/WHEEL
acryo-0.6.0.dist-info/licenses/LICENSE
acryo-0.6.0.dist-info/RECORD
