Metadata-Version: 2.4
Name: acryo
Version: 0.6.0
Summary: An extensible cryo-EM/ET toolkit for Python.
Author-email: Hanjin Liu <liuhanjin.sc@gmail.com>
License: BSD 3-Clause License
License-File: LICENSE
Classifier: Programming Language :: Python :: 3 :: Only
Classifier: Programming Language :: Python :: 3.10
Classifier: Programming Language :: Python :: 3.11
Classifier: Programming Language :: Python :: 3.12
Classifier: Programming Language :: Python :: 3.13
Requires-Python: >=3.10
Requires-Dist: dask<2025.0.0
Requires-Dist: numpy>=2.2.4
Requires-Dist: polars>=1.35.1
Requires-Dist: scipy>=1.14.0
Requires-Dist: typing-extensions>=4.1.1
Provides-Extra: testing
Requires-Dist: mrcfile>=1.5.3; extra == 'testing'
Requires-Dist: pytest; extra == 'testing'
Requires-Dist: pytest-cov; extra == 'testing'
Requires-Dist: tifffile; extra == 'testing'
